README.md
setup.cfg
setup.py
key_shuffler/__init__.py
key_shuffler/shuffler.py
key_shuffler.egg-info/PKG-INFO
key_shuffler.egg-info/SOURCES.txt
key_shuffler.egg-info/dependency_links.txt
key_shuffler.egg-info/top_level.txt