Metadata-Version: 2.1
Name: key-shuffler
Version: 0.1.0
Summary: Simply python library for encrypting private keys using character shuffle method
Home-page: https://github.com/indicatedl/key_shuffler.git
Download-URL: https://github.com/indicatedl/key_shuffler/archive/refs/tags/v0.1.0.zip
Author: indicatedl
Author-email: indcated@gmail.com
License: MIT License
Classifier: Topic :: Communications :: Email
Classifier: Operating System :: OS Independent
Classifier: License :: OSI Approved :: MIT License
Classifier: Programming Language :: Python :: 3
Classifier: Programming Language :: Python :: 3.10
Classifier: Programming Language :: Python :: 3.11
Classifier: Intended Audience :: Developers
Classifier: Intended Audience :: Customer Service
Classifier: Intended Audience :: Financial and Insurance Industry
Requires-Python: >=3.10.0
